animals.py
tests/__init__.py
tests/test_animals.py
faker_animals-1.0.0.dist-info/LICENSE
faker_animals-1.0.0.dist-info/METADATA
faker_animals-1.0.0.dist-info/WHEEL
faker_animals-1.0.0.dist-info/top_level.txt
faker_animals-1.0.0.dist-info/RECORD
