Metadata-Version: 2.1
Name: faker_animals
Version: 1.0.0
Summary: A provider for the python faker library to generate random animals data
Home-page: https://github.com/symeoniordanidis/faker_animals
Author: Symeon Iordanidis
Author-email: iordanidissimeon@gmail.com
License: MIT
Classifier: Programming Language :: Python :: 3
Classifier: License :: OSI Approved :: MIT License
License-File: LICENSE
Requires-Dist: faker
